ytools/__init__.py
ytools/ytools.py
ytools-1.0.0.data/scripts/ytools
ytools-1.0.0.dist-info/DESCRIPTION.rst
ytools-1.0.0.dist-info/METADATA
ytools-1.0.0.dist-info/RECORD
ytools-1.0.0.dist-info/WHEEL
ytools-1.0.0.dist-info/metadata.json
ytools-1.0.0.dist-info/top_level.txt
