Metadata-Version: 2.0
Name: ytools
Version: 1.0.0
Summary: Command-line tool for selectively dumping nodes from `yaml` (or `json`) documents in `yaml` or `json` format.
Home-page: https://github.com/ytools/ynot
Author: Jakob Stemberger
Author-email: yaccob@gmx.net
License: Apache 2.0
Download-URL: https://github.com/yaccob/ytools/archive/1.0.0.tar.gz
Keywords: yaml,json,transform,xslt,jsonpath,json-path,dump,convert,validate,schema
Platform: UNKNOWN
Classifier: Programming Language :: Python :: 2.7
Requires-Dist: PyYaml
Requires-Dist: jsonpath-ng
Requires-Dist: jsonschema
Requires-Dist: strict-rfc3339
